fl/__init__.py
fl/_modidx.py
fl/core.py
flui-0.0.1.dist-info/licenses/LICENSE
flui-0.0.1.dist-info/METADATA
flui-0.0.1.dist-info/WHEEL
flui-0.0.1.dist-info/entry_points.txt
flui-0.0.1.dist-info/top_level.txt
flui-0.0.1.dist-info/RECORD
